woc/__init__.py
woc/bitcoin_rpc_class.py
woc/dialog.ui
woc/main.py
woc/write.py
writeonchain-0.0.1.dist-info/LICENSE
writeonchain-0.0.1.dist-info/METADATA
writeonchain-0.0.1.dist-info/WHEEL
writeonchain-0.0.1.dist-info/entry_points.txt
writeonchain-0.0.1.dist-info/top_level.txt
writeonchain-0.0.1.dist-info/RECORD
