Metadata-Version: 2.1
Name: writeonchain
Version: 0.0.1
Summary: Write your messages on public blockchain (BTC, LTC, Liquid).
Home-page: https://gitlab.com/valerio-vaccaro/writeonchain
Author: Valerio Vaccaro
Author-email: valerio.vaccaro@gmail.com
License: MIT
Classifier: Programming Language :: Python :: 3.7
Classifier: Operating System :: OS Independent
Requires-Python: >=3.7
License-File: LICENSE
Requires-Dist: certifi (==2022.9.24)
Requires-Dist: charset-normalizer (==2.1.1)
Requires-Dist: idna (==3.4)
Requires-Dist: PySide2 (==5.15.2.1)
Requires-Dist: requests (==2.28.1)
Requires-Dist: shiboken2 (==5.15.2.1)
Requires-Dist: urllib3 (==1.26.12)
